git_quick/__init__.py
git_quick/ai_commit.py
git_quick/cli.py
git_quick/config.py
git_quick/git_utils.py
git_quick/setup_wizard.py
git_quick/commands/__init__.py
git_quick/commands/story.py
git_quick/commands/sync.py
git_quick/commands/time_tracker.py
git_quick-1.4.0.dist-info/licenses/LICENSE
git_quick-1.4.0.dist-info/METADATA
git_quick-1.4.0.dist-info/WHEEL
git_quick-1.4.0.dist-info/entry_points.txt
git_quick-1.4.0.dist-info/top_level.txt
git_quick-1.4.0.dist-info/RECORD
