Metadata-Version: 2.4
Name: git-quick
Version: 1.4.0
Summary: Lightning-fast Git workflows with AI-powered commit messages
Author-email: Vishnu Swaroop <vswaroop04@gmail.com>
License: MIT
Project-URL: Homepage, https://github.com/vswaroop04/git-quick
Project-URL: Documentation, https://github.com/vswaroop04/git-quick#readme
Project-URL: Repository, https://github.com/vswaroop04/git-quick
Keywords: git,cli,productivity,ai,commit
Classifier: Development Status :: 3 - Alpha
Classifier: Intended Audience :: Developers
Classifier: License :: OSI Approved :: MIT License
Classifier: Programming Language :: Python :: 3
Classifier: Programming Language :: Python :: 3.8
Classifier: Programming Language :: Python :: 3.9
Classifier: Programming Language :: Python :: 3.10
Classifier: Programming Language :: Python :: 3.11
Requires-Python: >=3.8
License-File: LICENSE
Requires-Dist: click>=8.0
Requires-Dist: rich>=13.0
Requires-Dist: gitpython>=3.1
Requires-Dist: toml>=0.10
Requires-Dist: openai>=1.0
Requires-Dist: anthropic>=0.25
Requires-Dist: requests>=2.31
Requires-Dist: urllib3<2.0
Provides-Extra: dev
Requires-Dist: pytest>=7.0; extra == "dev"
Requires-Dist: pytest-cov>=4.0; extra == "dev"
Requires-Dist: black>=23.0; extra == "dev"
Requires-Dist: mypy>=1.0; extra == "dev"
Requires-Dist: ruff>=0.1; extra == "dev"
Dynamic: license-file
